aspire_bilby/__init__.py
aspire_bilby/plugin.py
aspire_bilby/utils.py
aspire_bilby-0.1.0a4.dist-info/licenses/LICENSE
aspire_bilby-0.1.0a4.dist-info/METADATA
aspire_bilby-0.1.0a4.dist-info/WHEEL
aspire_bilby-0.1.0a4.dist-info/entry_points.txt
aspire_bilby-0.1.0a4.dist-info/top_level.txt
aspire_bilby-0.1.0a4.dist-info/RECORD
