Metadata-Version: 2.4
Name: aspire-bilby
Version: 0.1.0a4
Author-email: "Michael J. Williams" <michaeljw1@googlemail.com>
License: MIT
Classifier: Programming Language :: Python :: 3
Requires-Python: >=3.9
License-File: LICENSE
Requires-Dist: bilby>=2.3.0
Requires-Dist: aspire-inference>=0.1.0a12
Requires-Dist: numpy
Requires-Dist: pandas
Provides-Extra: test
Requires-Dist: pytest; extra == "test"
Provides-Extra: torch
Requires-Dist: aspire-inference[torch]; extra == "torch"
Provides-Extra: jax
Requires-Dist: aspire-inference[jax]; extra == "jax"
Provides-Extra: minipcn
Requires-Dist: minipcn[array-api]>=0.2.0a3; extra == "minipcn"
Dynamic: license-file
